[
    {
        "id":"21",
        "titre":"html",
        "img":"https://i.postimg.cc/Prz91bHL/Html.png"
    },
    {
        "id":"22",
        "titre":"java",
        "img":"https://i.postimg.cc/TwrmwJL0/javascript.png"
    },
    {
        "id":"23",
        "titre":"REact",
        "img":"https://i.postimg.cc/N01sWJrg/React.png"
    },  
    {
        "id":"24",
        "titre":"Mongo",
        "img":"https://i.postimg.cc/qRRF8gr9/Mongo.png"
    },  
    {
        "id":"25",
        "titre":"Wordpress",
        "img":"https://i.postimg.cc/9QBR9QJP/wordpresss.png"
    },  
    {
        "id":"26",
        "titre":"git",
        "img":"https://i.postimg.cc/Wbk0dVBS/git.png"
    },  
    {
        "id":"27",
        "titre":"figma",
        "img":"https://i.postimg.cc/zG15rwwp/figma.png"
    },  
    {
        "id":"28",
        "titre":"SEO",
        "img":"https://i.postimg.cc/NFJ4xxst/seo.png"
    }

]